open_tool_client/__init__.py
open_tool_client-0.0.1.dist-info/METADATA
open_tool_client-0.0.1.dist-info/WHEEL
open_tool_client-0.0.1.dist-info/RECORD
